liga/sklearn/__init__.py
liga/sklearn/codegen.py
liga/sklearn/mlflow.py
liga/sklearn/models/__init__.py
liga/sklearn/models/classifier.py
liga/sklearn/models/cluster.py
liga/sklearn/models/regressor.py
liga/sklearn/models/transformer.py
liga_sklearn-0.3.0.dist-info/METADATA
liga_sklearn-0.3.0.dist-info/WHEEL
liga_sklearn-0.3.0.dist-info/namespace_packages.txt
liga_sklearn-0.3.0.dist-info/top_level.txt
liga_sklearn-0.3.0.dist-info/RECORD
