Metadata-Version: 2.1
Name: liga-sklearn
Version: 0.3.0
Requires-Python: <3.10,>=3.8
Requires-Dist: liga (<0.4.0,>=0.3.0)
Requires-Dist: scikit-learn
